hydra_base/__init__.py
hydra_base/config.py
hydra_base/exceptions.py
hydra_base/hydra.ini
hydra_base/hydra_logging.py
hydra_base/logging.conf
hydra_base/db/__init__.py
hydra_base/db/alembic.ini
hydra_base/db/audit.py
hydra_base/db/truncate.py
hydra_base/db/alembic/README
hydra_base/db/alembic/env.py
hydra_base/db/alembic/script.py.mako
hydra_base/db/alembic/versions/04e4ae80b7b9_project_inheritance.py
hydra_base/db/alembic/versions/08f0ebe40290_resource_attr_id.py
hydra_base/db/alembic/versions/1d3ab26415ec_template_status.py
hydra_base/db/alembic/versions/1eb51c6159ac_simplify_network.py
hydra_base/db/alembic/versions/21e8d704c020_roles_perms.py
hydra_base/db/alembic/versions/35088e32c557_rules.py
hydra_base/db/alembic/versions/3dc489a7eac1_scenario_id.py
hydra_base/db/alembic/versions/50bd5bac8701_add_tuser_failed_logins.py
hydra_base/db/alembic/versions/52d59176f0da_lengthen_names.py
hydra_base/db/alembic/versions/56ea2e814437_rule.py
hydra_base/db/alembic/versions/5e381835e382_templatetype_description.py
hydra_base/db/alembic/versions/6402bb82a531_unit_dimension_fk.py
hydra_base/db/alembic/versions/6883f6e39176_change_password_type.py
hydra_base/db/alembic/versions/6b24d6443e31_resourcegroupitem.py
hydra_base/db/alembic/versions/74ab69a8dcb6_user_user_id_user_id.py
hydra_base/db/alembic/versions/877adf863b33_project_appdata.py
hydra_base/db/alembic/versions/a48ad41579de_dataset_collection.py
hydra_base/db/alembic/versions/a7896842f484_template.py
hydra_base/db/alembic/versions/a81a860cda39_attribute_scoping.py
hydra_base/db/alembic/versions/b04cb2e57cb0_template_inheritance.py
hydra_base/db/alembic/versions/be206abd1412_project_id.py
hydra_base/db/alembic/versions/cec2b77ad85e_network_appdata.py
hydra_base/db/alembic/versions/d0c45fdc4fac_note.py
hydra_base/db/alembic/versions/d759891ddbf4_dataset_audit.py
hydra_base/db/alembic/versions/da2a4916c900_scenario_inheritance.py
hydra_base/db/alembic/versions/dd1110144e53_dataset_id.py
hydra_base-0.1.20.post0.dist-info/METADATA
hydra_base-0.1.20.post0.dist-info/WHEEL
hydra_base-0.1.20.post0.dist-info/top_level.txt
hydra_base-0.1.20.post0.dist-info/RECORD
