Metadata-Version: 2.4
Name: hydra-base
Version: 0.1.20.post0
Summary: Hydra Platform Base Library
Author-email: Stephen Knox <knoxsp@gmail.com>
Project-URL: Documentation, https://hydraplatform.org
Project-URL: Repository, https://github.com/hydraplatform/hydra-base
Requires-Python: >=3.8
Requires-Dist: bcrypt
Requires-Dist: lxml
Requires-Dist: pymongo
Requires-Dist: mysqlclient
Requires-Dist: python-dateutil
Requires-Dist: cheroot
Requires-Dist: beaker
Requires-Dist: click
Requires-Dist: diskcache
Requires-Dist: fsspec
Requires-Dist: h5py
Requires-Dist: lxml
Requires-Dist: mysqlclient
Requires-Dist: numpy
Requires-Dist: packaging
Requires-Dist: pandas
Requires-Dist: psycopg2-binary
Requires-Dist: pymongo
Requires-Dist: python-dateutil
Requires-Dist: requests
Requires-Dist: s3fs
Requires-Dist: sqlalchemy
Requires-Dist: tables
Requires-Dist: zope.sqlalchemy
